<ParameterList>

     <ParameterList name="Debug Output">

          <Parameter name="Write Resdiual to MatrixMarket"
                     type="int" 
                     value="0"/>

          <Parameter name="Write Jacobian to MatrixMarket"
                     type="int" 
                     value="0"/>

          <Parameter name="Write Residual to Standard Output"
                     type="int"
                     value="-0"/>

          <Parameter name="Write Jacobian to Standard Output"
                     type="int"
                     value="-0"/>

     </ParameterList>

<!-- Set constant scale factor to improve tangent conditioning ~~~~~~~~~~~~~~~~~~~~~~~~~~~~~~~~~ -->

     <ParameterList name="Scaling">

          <Parameter name="Scale" 
                     type="double" 
                     value="1e3"/>

     </ParameterList>


<!-- =========================================================================================== -->
<!-- Set options for Data Transfer Kit ~~~~~~~~~~~~~~~~~~~~~~~~~~~~~~~~~~~~~~~~~~~~~~~~~~~~~~~~~ -->
<!-- =========================================================================================== -->

     <ParameterList name="DataTransferKit">

          <Parameter name="Map Type" 
                     type="string" 
                     value="Consistent Interpolation"/>

          <ParameterList name="L2 Projection">

               <Parameter name="Integration Order" 
                          type="int" 
                          value="2"/>

          </ParameterList>

          <ParameterList name="Consistent Interpolation">

          </ParameterList>

          <ParameterList name="Point Cloud">

               <Parameter name="Map Type" 
                          type="string" 
                          value="Moving Least Square Reconstruction"/>

               <Parameter name="Basis Type" 
                          type="string" 
                          value="Wu"/>

               <Parameter name="Basis Order" 
                          type="int" 
                          value="4"/>

               <Parameter name="Spatial Dimension" 
                          type="int" 
                          value="3"/>

               <Parameter name="RBF Radius" 
                          type="double" 
                          value="1.0"/>

          </ParameterList>

          <ParameterList name="Search">

               <Parameter name="Track Missed Range Entities" 
                          type="bool" 
                          value="false"/>

               <Parameter name="Point Inclusion Tolerance" 
                          value="1.0e-12" 
                          type="double"/>

          </ParameterList>
          
     </ParameterList>


<!-- =========================================================================================== -->
<!-- Specify problem parameters ~~~~~~~~~~~~~~~~~~~~~~~~~~~~~~~~~~~~~~~~~~~~~~~~~~~~~~~~~~~~~~~~ -->
<!-- =========================================================================================== -->

     <ParameterList name="Problem">

<!-- ~~~~ Declare your Physics (What you intend to model)! ~~~~~~~~~~~~~~~~~~~~~~~~~~~~~~~~~~~~~ -->
  
          <Parameter name="Name" 
                     type="string" 
                     value="Mechanics 3D"/>

<!-- ~~~~ Have Phalanx output a graph of the used evaluators ~~~~~~~~~~~~~~~~~~~~~~~~~~~~~~~~~~~ -->
  
          <Parameter name="Phalanx Graph Visualization Detail" 
                     type="int" 
                     value="0"/>

<!-- ~~~~ XML filename with material definitions ~~~~~~~~~~~~~~~~~~~~~~~~~~~~~~~~~~~~~~~~~~~~~~~ -->
  
          <Parameter name="MaterialDB Filename" 
                     type="string" 
                     value="../CoupledSchwarz_Cubes_StudyOverlap_Cube0_Material.xml"/>



<!-- ~~~~~~~~~~~~~~~~~~~~~~~~~~~~~~~~~~~~~~~~~~~~~~~~~~~~~~~~~~~~~~~~~~~~~~~~~~~~~~~~~~~~~~~~~~~ -->
<!-- ~~~~ Set boundary conditions on node sets from the discretization which follows ~~~~~~~~~~~ -->
<!-- ~~~~~~~~~~~~~~~~~~~~~~~~~~~~~~~~~~~~~~~~~~~~~~~~~~~~~~~~~~~~~~~~~~~~~~~~~~~~~~~~~~~~~~~~~~~ -->
  
          <ParameterList name="Dirichlet BCs">

<!-- ~~~~~~~~~ Specify symmetry condition on negative x surface ~~~~~~~~~~~~~~~~~~~~~~~~~~~~~~~~ -->
  
               <Parameter name="DBC on NS nodelist_5 for DOF X"
                          type="double" 
                         value="0.0"/>

<!-- ~~~~~~~~~ Specify symmetry condition on negative y surface ~~~~~~~~~~~~~~~~~~~~~~~~~~~~~~~~ -->
      
               <Parameter name="DBC on NS nodelist_5 for DOF Y"
                          type="double" 
                          value="0.0"/>

<!-- ~~~~~~~~~ Rollers on negative z surface ~~~~~~~~~~~~~~~~~~~~~~~~~~~~~~~~~~~~~~~~~~~~~~~~~~~ -->
      
               <Parameter name="DBC on NS nodelist_5 for DOF Z"
                          type="double" 
                          value="0.0"/>

<!-- ~~~~~~~~~ Schwarz BC on positive z surface ~~~~~~~~~~~~~~~~~~~~~~~~~~~~~~~~~~~~~~~~~~~~~~~~ -->

               <ParameterList name="DBC on NS nodelist_6 for DOF Schwarz">

                    <Parameter name="BC Function" 
                               type="string" 
                               value="Schwarz"/>

<!-- ~~~~~~~~~~~~~~ Define coupled domain for Schwarz BC ~~~~~~~~~~~~~~~~~~~~~~~~~~~~~~~~~~~~~~~ -->

                    <Parameter name="Coupled Application" 
                               type="string" 
                               value="CoupledSchwarz_Cubes_StudyOverlap_Cube1_Model.xml"/>

                    <Parameter name="Coupled Block" 
                               type="string" 
                               value="coarse"/>

               </ParameterList>

          </ParameterList>
    
     </ParameterList>



<!-- =========================================================================================== -->
<!-- Discretization and i/o information ~~~~~~~~~~~~~~~~~~~~~~~~~~~~~~~~~~~~~~~~~~~~~~~~~~~~~~~~ -->
<!-- =========================================================================================== -->

     <ParameterList name="Discretization">

          
          <Parameter name="Number Of Time Derivatives" 
                     type="int" 
                     value="1"/>

          <Parameter name="Method" 
                     type="string" 
                     value="Ioss"/>

          <Parameter name="Exodus Input File Name"
                     type="string" 
                     value="../CoupledSchwarz_Cubes_StudyOverlap_Cube0.g"/>

          <Parameter name="Exodus Output File Name"
                     type="string" 
                     value="CoupledSchwarz_Cubes_StudyOverlap_Cube0.e"/>

          <Parameter name="Exodus Solution Name" 
                     type="string" 
                     value="disp"/>

          <Parameter name="Exodus Residual Name" 
                     type="string" 
                     value="resid"/>

          <Parameter name="Separate Evaluators by Element Block"
                     type="bool" 
                     value="true"/>

     </ParameterList>
  
</ParameterList>
